{
  "name": "口播脚本打磨",
  "icon": "🎙️",
  "slot": "armor",
  "desc": "真实主播的数字分身 + 脚本打磨助手。三步对话：选题 → 出稿 → polish。不自主生产、不发帖、不巡检。",
  "requiresMcp": [
    "media-data-pack"
  ],
  "subSkills": [
    {
      "name": "综合选题",
      "icon": "🎯",
      "file": "综合选题.md",
      "desc": "主播问'今天选什么'时调用。跨 bot 聚合脚本 + MDP 热点采样 + 5 维打分。"
    },
    {
      "name": "MDP 检索策略",
      "icon": "🔍",
      "file": "MDP-检索策略.md",
      "desc": "weixin 事实底 + 抖音结构底 的双源 query 模板。"
    },
    {
      "name": "口播骨架",
      "icon": "📜",
      "file": "口播骨架.md",
      "desc": "500-2500 字骨架 + ==/**/![]/【音效】 四种标记语法 + 正反例。"
    },
    {
      "name": "历史风格参考",
      "icon": "🎨",
      "file": "历史风格参考.md",
      "desc": "从 12 篇历史样本抽的句式 / 金句 / 钩子 / CTA 片段库。polish 用。"
    }
  ]
}
